build/lib/guapow/__init__.py
build/lib/guapow/cli/__init__.py
build/lib/guapow/cli/args.py
build/lib/guapow/cli/command.py
build/lib/guapow/cli/main.py
build/lib/guapow/cli/commands/__init__.py
build/lib/guapow/cli/commands/optimizer.py
build/lib/guapow/cli/commands/profile.py
build/lib/guapow/cli/commands/service.py
build/lib/guapow/cli/commands/watcher.py
build/lib/guapow/common/__init__.py
build/lib/guapow/common/auth.py
build/lib/guapow/common/class_util.py
build/lib/guapow/common/config.py
build/lib/guapow/common/dto.py
build/lib/guapow/common/encoder.py
build/lib/guapow/common/encryption.py
build/lib/guapow/common/log.py
build/lib/guapow/common/model.py
build/lib/guapow/common/model_util.py
build/lib/guapow/common/network.py
build/lib/guapow/common/profile.py
build/lib/guapow/common/scripts.py
build/lib/guapow/common/steam.py
build/lib/guapow/common/system.py
build/lib/guapow/common/users.py
build/lib/guapow/common/util.py
build/lib/guapow/runner/__init__.py
build/lib/guapow/runner/main.py
build/lib/guapow/runner/profile.py
build/lib/guapow/runner/settings.py
build/lib/guapow/runner/task.py
build/lib/guapow/service/__init__.py
build/lib/guapow/service/optimizer/__init__.py
build/lib/guapow/service/optimizer/cpu.py
build/lib/guapow/service/optimizer/flow.py
build/lib/guapow/service/optimizer/gpu.py
build/lib/guapow/service/optimizer/handler.py
build/lib/guapow/service/optimizer/launcher.py
build/lib/guapow/service/optimizer/main.py
build/lib/guapow/service/optimizer/mouse.py
build/lib/guapow/service/optimizer/profile.py
build/lib/guapow/service/optimizer/renicer.py
build/lib/guapow/service/optimizer/watch.py
build/lib/guapow/service/optimizer/win_compositor.py
build/lib/guapow/service/optimizer/post_process/__init__.py
build/lib/guapow/service/optimizer/post_process/context.py
build/lib/guapow/service/optimizer/post_process/summary.py
build/lib/guapow/service/optimizer/post_process/task.py
build/lib/guapow/service/optimizer/task/__init__.py
guapow-1.3.5.dist-info/licenses/LICENSE
guapow-1.3.5.dist-info/METADATA
guapow-1.3.5.dist-info/WHEEL
guapow-1.3.5.dist-info/entry_points.txt
guapow-1.3.5.dist-info/top_level.txt
guapow-1.3.5.dist-info/RECORD
