Metadata-Version: 2.4
Name: guapow
Version: 1.3.5
Summary: On-demand and auto performance optimizer for Linux applications
Home-page: https://github.com/vinifmor/guapow
Author: Vinícius Moreira
Author-email: Vinicius Moreira <vinicius_fmoreira@hotmail.com>
License:                   Copyright (c) 2021 Vinícius Moreira
Project-URL: Repository, https://github.com/vinifmor/guapow
Classifier: Topic :: Utilities
Classifier: Programming Language :: Python
Classifier: Programming Language :: Python :: 3.8
Classifier: Programming Language :: Python :: 3.9
Classifier: Programming Language :: Python :: 3.10
Classifier: Programming Language :: Python :: 3.11
Requires-Python: >=3.8
License-File: LICENSE
Requires-Dist: aiofiles>=0.7.0
Requires-Dist: aiohttp>=3.7.0
Requires-Dist: pycryptodome>=3.10.1
Dynamic: author
Dynamic: home-page
Dynamic: license-file
Dynamic: requires-python
